CONTRIBUTING.md
COPYING.txt
ChangeLog.md
MANIFEST.in
README.md
setup.py
doc/Makefile
doc/README
doc/conf.py
doc/index.rst
doc/_static/PoweredByPycogent.jpg
doc/_static/basic.css
doc/_static/default.css
doc/_static/favicon.ico
doc/_static/google_feed.js
doc/_static/powered_by_skbio.png
doc/_static/qiime_logo_large.png
doc/_static/wordpressheader.png
doc/_static/Examples/File_Formats/Example_ID_to_Taxonomy_mapping_File.txt
doc/_static/Examples/File_Formats/Example_Mapping_File.txt
doc/_static/Examples/File_Formats/Fasting_Map_reverse_primers.txt
doc/_static/Examples/File_Formats/example_fasta_after_split_libraries.fna
doc/_templates/layout.html
doc/developer/index.rst
doc/developer/script_testing.rst
doc/documentation/biom_format.rst
doc/documentation/file_formats.rst
doc/documentation/index.rst
doc/documentation/qiime_parameters_files.rst
doc/documentation/script_index.rst
doc/documentation/table_objects.rst
doc/images/UPGMAbytreatment.png
doc/images/barchart1.png
doc/images/biplot.png
doc/images/boottree.png
doc/images/configure_ebs_volume_attachment.png
doc/images/configure_ebs_volume_creation.png
doc/images/create_an_ebs_volume.png
doc/images/cyberduck_create_output_file.png
doc/images/cyberduck_drag_and_drop_input_file.png
doc/images/cyberduck_drag_and_drop_output_file.png
doc/images/cyberduck_open_connection.png
doc/images/cyberduck_opened_connection.png
doc/images/cyberduck_view_file.png
doc/images/cytoscape_change_background.png
doc/images/cytoscape_colored_edges.png
doc/images/cytoscape_colored_shared.png
doc/images/cytoscape_initial_network.png
doc/images/cytoscape_nodecolor.png
doc/images/distance_boxplots1.png
doc/images/example_primer_construct.png
doc/images/favicon.ico
doc/images/fisheyeheatmap.png
doc/images/header.png
doc/images/heatmap.png
doc/images/hiarchclust.png
doc/images/jackpcoa.png
doc/images/mantel_correlogram.png
doc/images/network.png
doc/images/pcoa1.png
doc/images/procrustes_tutorial_figure1.png
doc/images/public_dns_entry.png
qiime.egg-info/PKG-INFO
qiime.egg-info/SOURCES.txt
qiime.egg-info/dependency_links.txt
qiime.egg-info/requires.txt
qiime.egg-info/top_level.txt
