Metadata-Version: 1.1
Name: qiime
Version: 1.9.1
Summary: Quantitative Insights Into Microbial Ecology
Home-page: http://www.qiime.org
Author: QIIME development team
Author-email: qiime.help@gmail.com
License: GPL
Keywords: bioinformatics,microbiome,microbiology,qiime
Platform: MacOS
Platform: Linux
Classifier: Development Status :: 5 - Production/Stable
Classifier: Environment :: Console
Classifier: License :: OSI Approved :: GNU General Public License v2 (GPLv2)
Classifier: Topic :: Scientific/Engineering :: Bio-Informatics
Classifier: Programming Language :: Python
Classifier: Programming Language :: Python :: 2.7
Classifier: Operating System :: Unix
Classifier: Operating System :: MacOS :: MacOS X
Classifier: Operating System :: POSIX
